ambit_stochastics/__init__.py
ambit_stochastics/simple_ambit_field.py
ambit_stochastics/trawl.py
ambit_stochastics/helpers/Laplace_transform_inversion.py
ambit_stochastics/helpers/__init__.py
ambit_stochastics/helpers/acf_functions.py
ambit_stochastics/helpers/adaptive_rejection_sampling.py
ambit_stochastics/helpers/adaptive_rejection_sampling_secanats.py
ambit_stochastics/helpers/adaptive_rejection_sampling_tangents.py
ambit_stochastics/helpers/adrp.py
ambit_stochastics/helpers/alternative_convolution_implementation.py
ambit_stochastics/helpers/cov_estimator.py
ambit_stochastics/helpers/densities.py
ambit_stochastics/helpers/forecasting_helpers.py
ambit_stochastics/helpers/gaussian_approx.py
ambit_stochastics/helpers/input_checks.py
ambit_stochastics/helpers/loss_functions.py
ambit_stochastics/helpers/marginal_distribution_functions.py
ambit_stochastics/helpers/mode_aux.py
ambit_stochastics/helpers/sampler.py
Ambit_Stochastics-1.0.7.dist-info/LICENSE
Ambit_Stochastics-1.0.7.dist-info/METADATA
Ambit_Stochastics-1.0.7.dist-info/WHEEL
Ambit_Stochastics-1.0.7.dist-info/top_level.txt
Ambit_Stochastics-1.0.7.dist-info/RECORD
