Metadata-Version: 2.1
Name: Ambit-Stochastics
Version: 1.0.7
Summary: A pacakge dedicated to the study of Ambit fields and Trawl processes
Home-page: https://github.com/danleonte/Ambit_Stochastics
Author: Dan Leonte
Author-email: dleonte97@gmail.com
Project-URL: Bug Tracker, https://github.com/danleonte/Ambit_Stochastics/issues
Classifier: Programming Language :: Python :: 3
Classifier: License :: OSI Approved :: MIT License
Classifier: Operating System :: OS Independent
Requires-Python: >=3.5
License-File: LICENSE
